towebm/__init__.py
towebm/_version.py
towebm/argparsers.py
towebm/converters.py
towebm/ffcat.py
towebm/formats.py
towebm/toav1.py
towebm/toflac.py
towebm/tomp3.py
towebm/toopus.py
towebm/tovorbis.py
towebm/towebm.py
towebm-2.0.0.dist-info/METADATA
towebm-2.0.0.dist-info/WHEEL
towebm-2.0.0.dist-info/entry_points.txt
towebm-2.0.0.dist-info/licenses/LICENSE.txt
towebm-2.0.0.dist-info/RECORD
