Metadata-Version: 2.4
Name: towebm
Version: 2.0.0
Summary: Python 3 scripts which use ffmpeg to convert videos to webm format (vp9+opus) or to convert audio to opus or vorbis.
Project-URL: Homepage, https://github.com/dgasaway/towebm
Project-URL: Issues, https://github.com/dgasaway/towebm/issues
Project-URL: Download, https://github.com/dgasaway/towebm/releases
Author-email: David Gasaway <dave@gasaway.org>
License-Expression: GPL-2.0-or-later
License-File: LICENSE.txt
Keywords: audio,av1,converter,ffmpeg,flac,mp3,opus,video,vorbis,vp9,webm
Classifier: Development Status :: 5 - Production/Stable
Classifier: Environment :: Console
Classifier: Intended Audience :: End Users/Desktop
Classifier: License :: OSI Approved :: GNU General Public License v2 or later (GPLv2+)
Classifier: Operating System :: OS Independent
Classifier: Programming Language :: Python :: 3
Classifier: Programming Language :: Python :: 3 :: Only
Classifier: Programming Language :: Python :: 3.8
Classifier: Topic :: Multimedia :: Sound/Audio :: Conversion
Classifier: Topic :: Multimedia :: Video :: Conversion
Requires-Python: >=3.8
